brunoais/apispec/ext/decorated_crawler.py
apispec_decorated_crawler-2.0.0.dist-info/LICENSE
apispec_decorated_crawler-2.0.0.dist-info/METADATA
apispec_decorated_crawler-2.0.0.dist-info/WHEEL
apispec_decorated_crawler-2.0.0.dist-info/top_level.txt
apispec_decorated_crawler-2.0.0.dist-info/RECORD
