Metadata-Version: 2.1
Name: apispec-decorated-crawler
Version: 2.0.0
Summary: Plugin for apispec which helps reusing the documentation by using a decorated function stack.
Home-page: https://github.com/brunoais/apispec-decorated-crawler
Author: Brunoais
Author-email: brunoaiss@gmail.com
License: MIT
Platform: UNKNOWN
Classifier: Programming Language :: Python :: 3
Classifier: Programming Language :: Python :: 3.6
Classifier: Programming Language :: Python :: 3.7
Classifier: License :: OSI Approved :: MIT License
Classifier: Operating System :: OS Independent
Requires-Dist: apispec (~=1.0)
